naff_yt_audio/__init__.py
naff_yt_audio/main.py
naff_ytaudio-1.0.0.dist-info/LICENSE.md
naff_ytaudio-1.0.0.dist-info/METADATA
naff_ytaudio-1.0.0.dist-info/WHEEL
naff_ytaudio-1.0.0.dist-info/top_level.txt
naff_ytaudio-1.0.0.dist-info/RECORD
